extra_streamlit_components/__init__.py
extra_streamlit_components/BouncingImage/__init__.py
extra_streamlit_components/BouncingImage/frontend/build/asset-manifest.json
extra_streamlit_components/BouncingImage/frontend/build/bootstrap.min.css
extra_streamlit_components/BouncingImage/frontend/build/index.html
extra_streamlit_components/BouncingImage/frontend/build/precache-manifest.71d73dc7cd1a4ecf975228631f38237c.js
extra_streamlit_components/BouncingImage/frontend/build/service-worker.js
extra_streamlit_components/BouncingImage/frontend/build/static/js/2.44d5bbe2.chunk.js
extra_streamlit_components/BouncingImage/frontend/build/static/js/2.44d5bbe2.chunk.js.LICENSE.txt
extra_streamlit_components/BouncingImage/frontend/build/static/js/2.44d5bbe2.chunk.js.map
extra_streamlit_components/BouncingImage/frontend/build/static/js/main.b57f7b4b.chunk.js
extra_streamlit_components/BouncingImage/frontend/build/static/js/main.b57f7b4b.chunk.js.map
extra_streamlit_components/BouncingImage/frontend/build/static/js/runtime-main.11d11adb.js
extra_streamlit_components/BouncingImage/frontend/build/static/js/runtime-main.11d11adb.js.map
extra_streamlit_components/CookieManager/__init__.py
extra_streamlit_components/CookieManager/frontend/build/asset-manifest.json
extra_streamlit_components/CookieManager/frontend/build/bootstrap.min.css
extra_streamlit_components/CookieManager/frontend/build/index.html
extra_streamlit_components/CookieManager/frontend/build/static/js/2.03f21fe6.chunk.js
extra_streamlit_components/CookieManager/frontend/build/static/js/2.03f21fe6.chunk.js.LICENSE.txt
extra_streamlit_components/CookieManager/frontend/build/static/js/2.03f21fe6.chunk.js.map
extra_streamlit_components/CookieManager/frontend/build/static/js/main.11724073.chunk.js
extra_streamlit_components/CookieManager/frontend/build/static/js/main.11724073.chunk.js.map
extra_streamlit_components/CookieManager/frontend/build/static/js/runtime-main.870aa37f.js
extra_streamlit_components_better_cookie_manager-0.0.10.dist-info/LICENSE
extra_streamlit_components_better_cookie_manager-0.0.10.dist-info/METADATA
extra_streamlit_components_better_cookie_manager-0.0.10.dist-info/WHEEL
extra_streamlit_components_better_cookie_manager-0.0.10.dist-info/top_level.txt
extra_streamlit_components_better_cookie_manager-0.0.10.dist-info/RECORD
