Metadata-Version: 2.1
Name: extra-streamlit-components-better-cookie-manager
Version: 0.0.10
Summary: An all-in-one place, to find complex or just natively unavailable components on streamlit.
Home-page: https://github.com/matheusfillipe/Extra-Streamlit-Components
Author: Mohamed Abdou
Author-email: matex512@gmail.com
Keywords: Python,Streamlit,React,JavaScript
Classifier: Programming Language :: Python :: 3
Classifier: License :: OSI Approved :: MIT License
Classifier: Operating System :: OS Independent
Requires-Python: >=3.6
License-File: LICENSE
Requires-Dist: streamlit (>=0.86)
